recursive_size/__init__.py
recursive_size-1.2.dist-info/LICENSE
recursive_size-1.2.dist-info/METADATA
recursive_size-1.2.dist-info/WHEEL
recursive_size-1.2.dist-info/top_level.txt
recursive_size-1.2.dist-info/RECORD
